setup.cfg
setup.py
Themis_docs.egg-info/PKG-INFO
Themis_docs.egg-info/SOURCES.txt
Themis_docs.egg-info/dependency_links.txt
Themis_docs.egg-info/not-zip-safe
Themis_docs.egg-info/requires.txt
Themis_docs.egg-info/top_level.txt
themis_doc/__init__.py
themis_doc/api/__init__.py
themis_doc/models/__init__.py
themis_doc/models/document.py
themis_doc/models/template.py
themis_doc/pdf_storage/__init__.py
themis_doc/pdf_storage/s3.py