Metadata-Version: 2.1
Name: Themis-docs
Version: 0.0.11
Summary: Docs  template generator
Home-page: https://github.com/jetbridge/themis
Author: JetBridge
Author-email: adam@jetbridge.com
License: ABRMS
Platform: any
Requires-Python: >=3.6.0
